accolades/__init__.py
accolades/example.py
accolades-100.0.1.dist-info/LICENSE
accolades-100.0.1.dist-info/METADATA
accolades-100.0.1.dist-info/WHEEL
accolades-100.0.1.dist-info/top_level.txt
accolades-100.0.1.dist-info/RECORD
