Metadata-Version: 2.1
Name: accolades
Version: 100.0.1
Summary: An example package
Author-email: David <blessed.0-printer@icloud.com>
License: MIT License        
Project-URL: Homepage, https://github.com/pypa/sampleproject
Project-URL: Bug Tracker, https://github.com/pypa/sampleproject/issues
Classifier: Programming Language :: Python :: 3
Classifier: License :: OSI Approved :: MIT License
Classifier: Operating System :: OS Independent
Requires-Python: >=3.6
License-File: LICENSE
